lemonpie/__init__.py
lemonpie/_nbdev.py
lemonpie/basics.py
lemonpie/data.py
lemonpie/experiment.py
lemonpie/learn.py
lemonpie/metrics.py
lemonpie/models.py
lemonpie/preprocessing/__init__.py
lemonpie/preprocessing/clean.py
lemonpie/preprocessing/transform.py
lemonpie/preprocessing/vocab.py
lemonpie-0.1.2.dist-info/LICENSE
lemonpie-0.1.2.dist-info/METADATA
lemonpie-0.1.2.dist-info/WHEEL
lemonpie-0.1.2.dist-info/entry_points.txt
lemonpie-0.1.2.dist-info/top_level.txt
lemonpie-0.1.2.dist-info/RECORD
