Metadata-Version: 2.1
Name: lemonpie
Version: 0.1.2
Summary: An open source deep learning library for Electronic Health Record (EHR) data
Home-page: https://github.com/corazonlabs/lemonpie/tree/main/
Author: Vinod
Author-email: vinod@corazonlabs.ai
License: Apache Software License 2.0
Keywords: ehr machine learning deep learning
Platform: UNKNOWN
Classifier: Development Status :: 3 - Alpha
Classifier: Intended Audience :: Developers
Classifier: License :: OSI Approved :: Apache Software License
Classifier: Natural Language :: English
Classifier: Programming Language :: Python :: 3.6
Classifier: Programming Language :: Python :: 3.7
Classifier: Programming Language :: Python :: 3.8
Requires-Python: >=3.6
Requires-Dist: pandas (>=1.2.2)
Requires-Dist: addict (>=2.3.0)
Requires-Dist: fastai (<2.0.0)
Requires-Dist: torchvision
Requires-Dist: matplotlib
Requires-Dist: requests
Requires-Dist: pyyaml
Requires-Dist: scikit-learn
